[
  { 
    "name": "AFC Bournemouth",
    "code": "AFCB",
    "website": "http://www.afcb.co.uk/",
    "crestURL": "https://upload.wikimedia.org/wikipedia/de/4/41/Afc_bournemouth.svg",
    "stadium": "Vitality Stadium",
    "latlng": [
      50.735278, 
      -1.838333
    ],
    "pubs": [
      {
        "name": "The George Tapps",
        "address": "207-215 Old Christchurch Rd, Bournemouth BH1 1JZ",
        "phoneNumber": "+44 1202 438001",
        "website": "http://www.georgetappsbournemouth.co.uk/",
        "latlng": [
          50.7224269,
          -1.8705347
        ]
      },
      {
        "name": "The Queens Park Hotel",
        "address": "482 Holdenhurst Road, Bournemouth, BH8 9AR",
        "phoneNumber": "+44 1202 397733",
        "website": "",
        "latlng": [
         50.7352099,
         -1.8470878
       ]
      },
      {
        "name": "The Bell",
        "address": "915 Christchurch Rd, Bournemouth, BH7 6AX",
        "phoneNumber": "+44 1202 427762",
        "website": "",
        "latlng": [
          50.7307303,
          -1.8272306
        ]
      }
    ],
    "foodOutlets": [
      {
        "name": "xxl food",
        "address": "512A Christchurch Rd, Bournemouth, BH1 4BE",
        "phoneNumber": "01202 914450",
        "website": "http://xxlfood.co.uk/",
        "latlng": [
          50.7278517,
          -1.8815212
        ]
      },
      {
        "name": "Cafe Culture",
        "address": "668 Christchurch Rd, Bournemouth, BH7 6BT",
        "phoneNumber": "01202 395144",
        "website": "",
        "latlng": [
         50.7278517,
         -1.8815212
       ]
      }
    ],
    "hotels": [
      {
        "name": "The Portman Hotel",
        "address": "97 Ashley Rd, Bournemouth, BH1 4LT",
        "phoneNumber": "01202 397114",
        "website": "",
        "latlng": [
          50.7303588,
          -1.8427474
        ]
      },
      {
        "name": "The Queens Park Hotel",
        "address": "482 Holdenhurst Road, Bournemouth, BH8 9AR",
        "phoneNumber": "+44 1202 397733",
        "website": "",
        "latlng": [
         50.7352099,
         -1.8470878
       ]
      }
    ]
  },

  { 
    "name": "Arsenal",
    "code": "AFC",
    "website": "http://www.arsenal.com/",
    "crestURL": "http://upload.wikimedia.org/wikipedia/en/5/53/Arsenal_FC.svg",
    "stadium": "Emirates Stadium",
    "latlng": [
      51.555, 
      -0.108611 
    ],
    "pubs": [
      {
        "name": "The Horatia",
        "address": "98-102 Holloway Rd, Highbury East, London N7 8JE",
        "phoneNumber": "020 7682 4857",
        "website": "http://www.thehoratia.co.uk/",
        "latlng": [
          51.5499799,
          -0.1106777
        ]
      },
      {
        "name": "The Drayton Arms",
        "address": "153 Old Brompton Rd, Kensington, London SW5 0LJ",
        "phoneNumber": "020 7835 2301",
        "website": "http://www.thedraytonarmssw5.co.uk/",
        "latlng": [
         51.5215936,
         -0.1793754
        ]
      },
      {
        "name": "The Coronet",
        "address": "28 New Kent Rd, London SE1 6TJ",
        "phoneNumber": "020 7701 1500",
        "website": "http://www.coronettheatre.co.uk/",
        "latlng": [
          51.4946616,
          -0.1008805
        ]
      }
    ],
    "foodOutlets": [
      {
        "name": "Domino's Pizza - London - Highbury",
        "address": "92 Hornsey Rd, London N7 7NN",
        "phoneNumber": "020 7700 3666",
        "website": "https://www.dominos.co.uk/pizzaservice/london-highbury.aspx",
        "latlng": [
          51.5562416,
          -0.113135
        ]
      },
      {
        "name": "Burger King",
        "address": "Nags Head Centre, Nags Head Shopping Centre, 408 Holloway Rd, London N7 6PZ",
        "phoneNumber": "020 7607 3725",
        "website": "http://www.burgerking.co.uk/",
        "latlng": [
         51.5452293,
         -0.1780442
        ]
      }
    ],
    "hotels": [
      {
        "name": "Five Kings Hotel",
        "address": "59 Anson Rd, London N7 0AR",
        "phoneNumber": "020 7607 3996",
        "website": "http://www.fivekingshotel.co.uk/",
        "latlng": [
          51.5553057,
          -0.1324028
        ]
      },
      {
        "name": "Finsbury Serviced Apartments",
        "address": "13 Goodwin St, London N4 3HQ",
        "phoneNumber": "020 7272 0248",
        "website": "http://www.finsburyapartments.com/",
        "latlng": [
         51.5641801,
         -0.110131
        ]
      }
    ]
  },

  { 
    "name": "Burnley FC",
    "code": "BFC",
    "website": "http://www.burnleyfootballclub.com/",
    "crestURL": "https://upload.wikimedia.org/wikipedia/en/0/02/Burnley_FC_badge.png",
    "stadium": "Turf Moor",
    "latlng": [
      53.789167, 
      -2.230278
    ],
    "pubs": [
      {
        "name": "The Boot Inn",
        "address": "18 St James's Ln, Burnley BB11 1NG",
        "phoneNumber": "01282 463720",
        "website": "https://www.jdwetherspoon.com/pubs/all-pubs/england/lancashire/the-boot-inn-burnley",
        "latlng": [
          53.7889462,
          -2.2430587
        ]
      },
      {
        "name": "Burnley Cricket Club",
        "address": "Belvedere Rd, Burnley BB10 4BN",
        "phoneNumber": "01282 422089",
        "website": "http://www.burnleycricketclub.com/",
        "latlng": [
         53.7897664,
         -2.2349331
       ]
      },
      {
        "name": "The Bridge Bier Huis",
        "address": "2 Bank Parade, Burnley BB11 1UH",
        "phoneNumber": "01282 411304",
        "website": "http://www.thebridgebierhuis.co.uk/",
        "latlng": [
          53.7901741,
          -2.2438903
        ]
      }
    ],
    "foodOutlets": [
      {
        "name": "Bertram's Restaurant",
        "address": "Royle Lodge, Crow Wood, Burnley BB12 0RT",
        "phoneNumber": "01282 471930",
        "website": "http://bertramsrestaurant.com/",
        "latlng": [
          53.8013733,
          -2.255594
        ]
      },
      {
        "name": "The Red Lantern",
        "address": "9 Bank Parade, Burnley BB11 1UH",
        "phoneNumber": "01282 426848",
        "website": "http://www.theredlantern.net/",
        "latlng": [
         53.7900527,
         -2.2435639
       ]
      }
    ],
    "hotels": [
      {
        "name": "Travelodge Hotel - Burnley",
        "address": "Barracks Rd, Burnley BB11 4SB",
        "phoneNumber": "0871 984 6125",
        "website": "https://www.travelodge.co.uk/hotels/118/Burnley-hotel?WT.tsrc=GHA_Organic&utm_campaign=GHA_Burnley&utm_medium=GHA_Organic&utm_source=google",
        "latlng": [
          53.7894941,
          -2.2627454
        ]
      },
      {
        "name": "BEST WESTERN Higher Trapp Country House Hotel",
        "address": "Trapp Ln, Simonstone, Burnley BB12 7QW",
        "phoneNumber": "01282 772781",
        "website": "http://www.lavenderhotels.co.uk/Higher-Trapp",
        "latlng": [
         53.816603,
         -2.3412237
        ]
      }
    ]
  },

  { 
    "name": "Chelsea FC",
    "code": "CFC",
    "website": "https://www.chelseafc.com/",
    "crestURL": "http://upload.wikimedia.org/wikipedia/de/5/5c/Chelsea_crest.svg",
    "stadium": "Stamford Bridge",
    "latlng": [
      51.481667,
      -0.191111
    ],
    "pubs": [
      {
        "name": "Courtfield",
        "address": "187 Earls Ct Rd, Earls Court SW5 9AN",
        "phoneNumber": "020 7370 2626",
        "website": "http://www.taylor-walker.co.uk/pub/courtfield-earls-court/c0612/?utm_source=g_places&utm_medium=link&utm_campaign=places&utm_content=c0612",
        "latlng": [
          51.4922048,
          -0.1948348
        ]
      },
      {
        "name": "The Blackbird",
        "address": "209 Earls Ct Rd, Earls Court, London SW5 9AN",
        "phoneNumber": "020 7835 1855",
        "website": "http://www.blackbirdearlscourt.co.uk/",
        "latlng": [
         51.4917473,
         -0.1943552
        ]
      },
      {
        "name": "The Prince of Teck",
        "address": "161 Earls Ct Rd, Kensington, London SW5 9RQ",
        "phoneNumber": "020 7373 4291",
        "website": "http://www.princeofteck.com/",
        "latlng": [
          51.4927851,
          -0.196024
        ]
      }
    ],
    "foodOutlets": [
      {
        "name": "KFC",
        "address": "96-102 Uxbridge Rd, White City, London W12 8LR",
        "phoneNumber": "020 8746 0820",
        "website": "https://www.kfc.co.uk/",
        "latlng": [
          51.5046839,
          -0.2233321
        ]
      },
      {
        "name": "McDonald's",
        "address": "Broadway Shopping Centre, 7-8 Hammersmith Broadway, London W6 9YD",
        "phoneNumber": "020 8563 1514",
        "website": "http://www.mcdonalds.co.uk/ukhome.html",
        "latlng": [
         51.492149,
         -0.2260727
        ]
      }
    ],
    "hotels": [
      {
        "name": "Holiday Inn Express London - Earl's Court",
        "address": "295 North End Rd, London W14 9NS",
        "phoneNumber": "020 7384 5151",
        "website": "https://www.ihg.com/holidayinnexpress/hotels/gb/en/london/lonec/hoteldetail?cm_mmc=GoogleMaps-_-EX-_-GBR-_-LONEC",
        "latlng": [
          51.4863279,
          -0.2048576
        ]
      },
      {
        "name": "La Reserve Hotel",
        "address": "422-428 Fulham Rd, Fulham, London SW6 1DU",
        "phoneNumber": "020 7385 8561",
        "website": "http://www.la-reservehotel.co.uk/home",
        "latlng": [
         51.4802924,
         -0.1932884
        ]
      }
    ]
  },

  { 
    "name": "Crystal Palace FC",
    "code": "CRY",
    "website": "http://www.cpfc.co.uk/",
    "crestURL": "http://upload.wikimedia.org/wikipedia/de/b/bf/Crystal_Palace_F.C._logo_(2013).png",
    "stadium": "Selhurst Park",
    "latlng": [
      51.398333,
      -0.085556
    ],
    "pubs": [
      {
        "name": "The Railway Telegraph",
        "address": "19 Brigstock Rd, Thornton Heath CR7 7JJ",
        "phoneNumber": "",
        "website": "",
        "latlng": [
          51.3980568,
          -0.1032437
        ]
      },
      {
        "name": "The Ship",
        "address": "47 High St, Croydon CR0 1QD",
        "phoneNumber": "020 8688 2810",
        "website": "http://www.shippub.co.uk/",
        "latlng": [
         51.3850991,
         -0.2335036
       ]
      },
      {
        "name": "Flora Sandes",
        "address": "Brigstock Rd, Thornton Heath CR7 7JG",
        "phoneNumber": "020 8689 6277",
        "website": "https://www.jdwetherspoon.com/",
        "latlng": [
          51.3982168,
          -0.1018565
        ]
      }
    ],
    "foodOutlets": [
      {
        "name": "Karachi Cuisine",
        "address": "1113-1115 London Rd, London SW16 4XD",
        "phoneNumber": "020 8689 6868",
        "website": "http://www.karachicuisine.com/",
        "latlng": [
          51.4020199,
          -0.1209941
        ]
      },
      {
        "name": "cappadocia",
        "address": "2, Station Buildings, Fife Rd, London KT1 1SW",
        "phoneNumber": "020 8549 6228",
        "website": "http://www.cappadociarestaurant.co.uk/",
        "latlng": [
         51.3980417,
         -0.3942578
        ]
      }
    ],
    "hotels": [
      {
        "name": "Atini Guest House",
        "address": "42 Grant Rd, Croydon CR0 6PG",
        "phoneNumber": "020 8656 2363",
        "website": "",
        "latlng": [
          
          
        ]
      },
      {
        "name": "Hotel ibis Styles London Croydon",
        "address": "",
        "phoneNumber": "",
        "website": "",
        "latlng": [
         51.3803139,
         -0.0806503
        ]
      }
    ]
  },

  { 
    "name": "Everton FC",
    "code": "EFC",
    "website": "http://www.evertonfc.com/",
    "crestURL": "http://upload.wikimedia.org/wikipedia/de/f/f9/Everton_FC.svg",
    "stadium": "Goodison Park",
    "latlng": [
      53.438889,
      -2.966389
    ],
    "pubs": [
      {
        "name": "The Thomas Frost Pub",
        "address": "177-187 Walton Rd, Liverpool L4 4AJ",
        "phoneNumber": "0151 207 8210",
        "website": "https://www.jdwetherspoon.com/pubs/all-pubs/england/merseyside/the-thomas-frost-liverpool",
        "latlng": [
          53.435996,
          -2.9748521
        ]
      },
      {
        "name": "Bradleys Wine Bar",
        "address": "158 Walton Rd, Liverpool L4 4AZ",
        "phoneNumber": "0151 207 5642",
        "website": "",
        "latlng": [
         53.4356002,
         -2.9746116
        ]
      },
      {
        "name": "The Richard John Blackler",
        "address": "Charlotte Row, 53 Great Charlotte St, Liverpool L1 1HU",
        "phoneNumber": "0151 709 4802",
        "website": "https://www.jdwetherspoon.com/",
        "latlng": [
          53.4060786,
          -2.9821259
        ]
      }
    ],
    "foodOutlets": [
      {
        "name": "The Boot Room Sports Cafe – Anfield",
        "address": "Liverpool Football Club, Anfield Rd, Liverpool L4 0TH",
        "phoneNumber": "0151 906 1892",
        "website": "http://bootroom.liverpoolfc.com/",
        "latlng": [
          53.4302573,
          -2.9639048
        ]
      },
      {
        "name": "Hot Wok",
        "address": "87 Langham St, Liverpool L4 4DA",
        "phoneNumber": "0151 207 5860",
        "website": "",
        "latlng": [
         53.4372762,
         -2.970041
        ]
      }
    ],
    "hotels": [
      {
        "name": "Stanley Park Hotel",
        "address": "27A Anfield Rd, Liverpool L4 0TF",
        "phoneNumber": "07810 100900",
        "website": "https://shouthotels.com/stanley-park-hotel-liverpool-england/",
        "latlng": [
          53.4330299,-2.9653242
        ]
      },
      {
        "name": "Hotel ibis Styles Liverpool Centre Dale Street",
        "address": "67 Dale St, Liverpool L2 2HJ",
        "phoneNumber": "0151 243 1720",
        "website": "http://www.accorhotels.com/gb/hotel-7601-ibis-styles-liverpool-centre-dale-street-cavern-quarter/index.shtml",
        "latlng": [
         53.408491,
         -2.9900173
       ]
      }
    ]
  },

  { 
    "name": "Hull City FC",
    "code": "HUL",
    "website": "http://www.hullcitytigers.com/",
    "crestURL": "http://upload.wikimedia.org/wikipedia/de/a/a9/Hull_City_AFC.svg",
    "stadium": "KCOM Stadium",
    "latlng": [
      53.746111,
      -0.367778
    ],
    "pubs": [
      {
        "name": "Brickmakers Arms",
        "address": "57-65 Walton St, Hull HU3 6JB",
        "phoneNumber": "01482 508913",
        "website": "",
        "latlng": [
          53.7455791,
          -0.3765638
        ]
      },
      {
        "name": "The Bowery",
        "address": "30-32 Princes Ave, Hull HU5 3QA",
        "phoneNumber": "01482 441126",
        "website": "http://www.marstons.co.uk/pubs/finder/",
        "latlng": [
         53.7539751,
         -0.3618384
        ]
      },
      {
        "name": "Editorial Inn",
        "address": "48 Spring Bank, Hull HU3 1AB",
        "phoneNumber": "01482 327738",
        "website": "",
        "latlng": [
          53.7491836,
          -0.3515977
        ]
      }
    ],
    "foodOutlets": [
      {
        "name": "The Madras Restaurant",
        "address": "249-251 Anlaby Rd, Hull HU3 2SE",
        "phoneNumber": "01482 213321",
        "website": "http://www.the-madras.com/",
        "latlng": [
          53.7431439,
          -0.3630857
        ]
      },
      {
        "name": "Bengal Lounge",
        "address": "31-33 Princes Ave, Hull HU5 3RX",
        "phoneNumber": "01482 473945",
        "website": "http://www.bengalloungeindian.co.uk/",
        "latlng": [
         53.7525583,
         -0.3631223
        ]
      }
    ],
    "hotels": [
      {
        "name": "The Gilson Hotel",
        "address": "11 Anlaby Rd, Hull HU1 2PJ",
        "phoneNumber": "01482 323299",
        "website": "http://www.gilsonhotel.co.uk/",
        "latlng": [
          53.7431099,
          -0.3471989
        ]
      },
      {
        "name": "The Kingston Theatre Hotel",
        "address": "1-2 Kingston Square, Hull HU2 8DA",
        "phoneNumber": "01482 225828",
        "website": "http://www.kingstontheatrehotel.com/",
        "latlng": [
         53.7476569,
         -0.3411236
        ]
      }
    ]
  },

  { 
    "name": "Leicester City FC",
    "code": "LCFC",
    "website": "http://www.lcfc.com/",
    "crestURL": "http://upload.wikimedia.org/wikipedia/en/6/63/Leicester02.png",
    "stadium": "King Power Stadium",
    "latlng": [
      52.620278,
      -1.142222
    ],
    "pubs": [
      {
        "name": "Soar Point",
        "address": "The Newarke, Leicester LE2 7BY",
        "phoneNumber": "0116 204 4911",
        "website": "http://www.thesoarpointleicester.co.uk/",
        "latlng": [
          52.6310089,
          -1.1506833
        ]
      },
      {
        "name": "Local Hero Flaming Grill",
        "address": "84 Aylestone Rd, Leicester LE2 7LB",
        "phoneNumber": "0116 275 5330",
        "website": "http://www.flaminggrillpubs.com/pub/local-hero-leicester/m6948/?utm_source=g_places&utm_medium=link&utm_campaign=places&utm_content=m6948",
        "latlng": [
         52.6208262,
         -1.1377255
        ]
      },
      {
        "name": "The Counting House",
        "address": "40 Almond Rd, Leicester LE2 7LH",
        "phoneNumber": "0116 275 5527",
        "website": "http://www.gkmeetandeat.co.uk/locations/counting-house-leicester/?utm_source=g_places&utm_medium=locations&utm_campaign=counting-house-leicester",
        "latlng": [
          52.6211501,
          -1.1352943
        ]
      }
    ],
    "foodOutlets": [
      {
        "name": "The White Peacock",
        "address": "16 King St, Leicester LE1 6RJ",
        "phoneNumber": "0116 254 7663",
        "website": "http://www.the-white-peacock.co.uk/",
        "latlng": [
          52.6313461,
          -1.1342948
        ]
      },
      {
        "name": "Shivalli",
        "address": "21 Welford Rd, Leicester LE2 7AD",
        "phoneNumber": "0116 255 0137",
        "website": "http://www.shivallirestaurant.com/",
        "latlng": [
         52.6309976,
         -1.1360767
        ]
      }
    ],
    "hotels": [
      {
        "name": "Premier Inn Leicester North West",
        "address": "Leicester Road, Leicester LE3 8HB",
        "phoneNumber": "0871 527 8598",
        "website": "http://www.premierinn.com/gb/en/hotels/england/leicestershire/leicester/leicester-north-west.html?cid=GLBC_LEIGYN",
        "latlng": [
          52.6574987,
          -1.1936447
        ]
      },
      {
        "name": "Holiday Inn Express Leicester",
        "address": "Filbert Way, Leicester LE2 7FL",
        "phoneNumber": "0116 249 4590",
        "website": "https://www.ihg.com/holidayinnexpress/hotels/gb/en/leicester/lctws/hoteldetail?cm_mmc=GoogleMaps-_-EX-_-GBR-_-LCTWS",
        "latlng": [
         52.6217523,
         -1.1450723
        ]
      }
    ]
  },

  { 
    "name": "Liverpool FC",
    "code": "LFC",
    "website": "http://www.liverpoolfc.com/",
    "crestURL": "http://upload.wikimedia.org/wikipedia/de/0/0a/FC_Liverpool.svg",
    "stadium": "Anfield",
    "latlng": [
      53.430828,
      -2.960847
    ],
    "pubs": [
      {
        "name": "The Cavern Pub",
        "address": "10 Mathew St, Liverpool L2 6RE",
        "phoneNumber": "0151 236 9091",
        "website": "https://www.cavernclub.org/",
        "latlng": [
          53.406376,
          -2.9903576
        ]
      },
      {
        "name": "The Richard John Blackler",
        "address": "Charlotte Row, 53 Great Charlotte St, Liverpool L1 1HU",
        "phoneNumber": "0151 709 4802",
        "website": "https://www.jdwetherspoon.com/",
        "latlng": [
         53.4060786,
         -2.9821259
        ]
      },
      {
        "name": "The Flat Iron",
        "address": "375-377 Walton Breck Rd, Liverpool L4 0SY",
        "phoneNumber": "",
        "website": "",
        "latlng": [
          53.4282015,
          -2.9565826
        ]
      }
    ],
    "foodOutlets": [
      {
        "name": "Kemps Bistro",
        "address": "Stanley Park, Anfield Rd, Liverpool L4 0TD",
        "phoneNumber": "0151 263 0363",
        "website": "http://theislagladstone.co.uk/kemps-bistro/",
        "latlng": [
          53.43369,
          -2.9692487
        ]
      },
      {
        "name": "Anfield Balti House",
        "address": "116 Breck Rd, Liverpool L4 2RD",
        "phoneNumber": "0151 222 1414",
        "website": "",
        "latlng": [
         53.4249124,
         -2.9564088
        ]
      }
    ],
    "hotels": [
      {
        "name": "Hotel Anfield",
        "address": "23 Anfield Road, Anfield, Liverpool, Merseyside L4 0TE",
        "phoneNumber": "0845 812 1234",
        "website": "",
        "latlng": [
          53.4332653,
          -2.9660451
        ]
      },
      {
        "name": "Stanley Park Hotel",
        "address": "27A Anfield Rd, Liverpool L4 0TF",
        "phoneNumber": "07810 100900",
        "website": "https://shouthotels.com/stanley-park-hotel-liverpool-england/",
        "latlng": [
         53.4330299,
         -2.9653242
        ]
      }
    ]
  },

  { 
    "name": "Manchester City FC",
    "code": "MCFC",
    "website": "https://www.mancity.com/",
    "crestURL": "https://upload.wikimedia.org/wikipedia/en/e/eb/Manchester_City_FC_badge.svg",
    "stadium": "The Etihad",
    "latlng": [
      53.483056,
      -2.200278
    ],
    "pubs": [
      {
        "name": "The Printworks",
        "address": "",
        "phoneNumber": "",
        "website": "",
        "latlng": [
          
          
        ]
      },
      {
        "name": "Yates’s",
        "address": "49 Portland St, Manchester M1 3LD",
        "phoneNumber": "",
        "website": "",
        "latlng": [
         
         
       ]
      },
      {
        "name": "Summerbee Bar",
        "address": "",
        "phoneNumber": "",
        "website": "",
        "latlng": [
          
          
        ]
      }
    ],
    "foodOutlets": [
      {
        "name": "Le Delicatezze Di Bruno",
        "address": "",
        "phoneNumber": "",
        "website": "",
        "latlng": [
          
          
        ]
      },
      {
        "name": "Pieminister",
        "address": "",
        "phoneNumber": "",
        "website": "",
        "latlng": [
         
        
       ]
      }
    ],
    "hotels": [
      {
        "name": "Hotel ibis budget Manchester Centre Pollard Street",
        "address": "",
        "phoneNumber": "",
        "website": "",
        "latlng": [
          
          
        ]
      },
      {
        "name": "Travelodge Hotel - Manchester Sportcity",
        "address": "",
        "phoneNumber": "",
        "website": "",
        "latlng": [
         
         
       ]
      }
    ]
  },

  { 
    "name": "Manchester United FC",
    "code": "MUFC",
    "website": "http://www.manutd.com/",
    "crestURL": "http://upload.wikimedia.org/wikipedia/de/d/da/Manchester_United_FC.svg",
    "stadium": "Old Trafford",
    "latlng": [
      53.463056,
      -2.291389
    ],
    "pubs": [
         {
           "name": "The Printworks",
           "address": "",
           "phoneNumber": "",
           "website": "",
           "latlng": [
             
             
           ]
         },
         {
           "name": "Yates’s",
           "address": "49 Portland St, Manchester M1 3LD",
           "phoneNumber": "",
           "website": "",
           "latlng": [
            
            
          ]
         },
         {
           "name": "Summerbee Bar",
           "address": "",
           "phoneNumber": "",
           "website": "",
           "latlng": [
             
             
           ]
         }
       ],
    "foodOutlets": [
      {
        "name": "Red Marrakech - Morroccan restaurant",
        "address": "",
        "phoneNumber": "",
        "website": "",
        "latlng": [
          
          
        ]
      },
      {
        "name": "Spices Of Kashmir (Old Trafford)",
        "address": "",
        "phoneNumber": "",
        "website": "",
        "latlng": [
         
        
       ]
      }
    ],
    "hotels": [
      {
        "name": "Chesters Hotel & Restaurant",
        "address": "",
        "phoneNumber": "",
        "website": "",
        "latlng": [
          
          
        ]
      },
      {
        "name": "Premier Inn Manchester Old Trafford",
        "address": "",
        "phoneNumber": "",
        "website": "",
        "latlng": [
         
         
       ]
      }
    ]
  },

  { 
    "name": "Middlesbrough FC",
    "code": "MID",
    "website": "http://www.mfc.co.uk/",
    "crestURL": "https://upload.wikimedia.org/wikipedia/en/2/2c/Middlesbrough_FC_crest.svg",
    "stadium": "Riverside Stadium",
    "latlng": [
      54.578333,
      -1.216944
    ],
    "pubs": [
      {
        "name": "The Isaac Wilson",
        "address": "",
        "phoneNumber": "",
        "website": "",
        "latlng": [
          
          
        ]
      },
      {
        "name": "Dr Browns",
        "address": "",
        "phoneNumber": "",
        "website": "",
        "latlng": [
         
         
       ]
      },
      {
        "name": "Lord Byron",
        "address": "",
        "phoneNumber": "",
        "website": "",
        "latlng": [
          
          
        ]
      }
    ],
    "foodOutlets": [
      {
        "name": "Brasserie Hudson Quay Bar-Restaurant",
        "address": "",
        "phoneNumber": "",
        "website": "",
        "latlng": [
          
          
        ]
      },
      {
        "name": "The Six Medals",
        "address": "",
        "phoneNumber": "",
        "website": "",
        "latlng": [
         
        
       ]
      }
    ],
    "hotels": [
      {
        "name": "Holiday Inn Express Middlesbrough - Centre Square",
        "address": "",
        "phoneNumber": "",
        "website": "",
        "latlng": [
          
          
        ]
      },
      {
        "name": "The Baltimore Hotel",
        "address": "",
        "phoneNumber": "",
        "website": "",
        "latlng": [
         
         
       ]
      }
    ]
  },

  { 
    "name": "Southampton FC",
    "code": "SFC",
    "website": "https://southamptonfc.com/",
    "crestURL": "http://upload.wikimedia.org/wikipedia/de/c/c9/FC_Southampton.svg",
    "stadium": "St Mary’s Stadium",
    "latlng": [
      50.905833,
      -1.391111
    ],
    "pubs": [
      {
        "name": "Yates's",
        "address": "113-117 Above Bar St, Southampton SO14 7FH",
        "phoneNumber": "",
        "website": "",
        "latlng": [
          
          
        ]
      },
      {
        "name": "The Standing Order",
        "address": "",
        "phoneNumber": "",
        "website": "",
        "latlng": [
         
         
       ]
      },
      {
        "name": "The Rockstone",
        "address": "",
        "phoneNumber": "",
        "website": "",
        "latlng": [
          
          
        ]
      }
    ],
    "foodOutlets": [
      {
        "name": "Turtle Bay Southampton",
        "address": "",
        "phoneNumber": "",
        "website": "",
        "latlng": [
          
          
        ]
      },
      {
        "name": "Fusion Noodle Bar",
        "address": "",
        "phoneNumber": "",
        "website": "",
        "latlng": [
         
        
       ]
      }
    ],
    "hotels": [
      {
        "name": "The Star Hotel",
        "address": "",
        "phoneNumber": "",
        "website": "",
        "latlng": [
          
          
        ]
      },
      {
        "name": "Jurys Inn Southampton",
        "address": "",
        "phoneNumber": "",
        "website": "",
        "latlng": [
         
         
       ]
      }
    ]
  },

  { 
    "name": "Stoke City FC",
    "code": "SCFC",
    "website": "http://www.stokecityfc.com/",
    "crestURL": "http://upload.wikimedia.org/wikipedia/de/a/a3/Stoke_City.svg",
    "stadium": "bet365 Stadium",
    "latlng": [
      52.988333,
      -2.175556
    ],
    "pubs": [
      {
        "name": "Longton Rugby Union Football Club",
        "address": "",
        "phoneNumber": "",
        "website": "",
        "latlng": [
          
          
        ]
      },
      {
        "name": "The Terrace",
        "address": "",
        "phoneNumber": "",
        "website": "",
        "latlng": [
         
         
       ]
      },
      {
        "name": "The Glebe",
        "address": "",
        "phoneNumber": "",
        "website": "",
        "latlng": [
          
          
        ]
      }
    ],
    "foodOutlets": [
      {
        "name": "Harvester Trentham Lakes",
        "address": "",
        "phoneNumber": "",
        "website": "",
        "latlng": [
          
          
        ]
      },
      {
        "name": "Frankie & Benny's",
        "address": "Trentham Gardens, Stone Road, Stoke-on-Trent ST4 8AX",
        "phoneNumber": "",
        "website": "",
        "latlng": [
         
        
       ]
      }
    ],
    "hotels": [
      {
        "name": "Holiday Inn Express Stoke on Trent",
        "address": "",
        "phoneNumber": "",
        "website": "",
        "latlng": [
          
          
        ]
      },
      {
        "name": "The Plough Motel",
        "address": "",
        "phoneNumber": "",
        "website": "",
        "latlng": [
         
         
       ]
      }
    ]
  },

  { 
    "name": "Sunderland AFC",
    "code": "SUN",
    "website": "https://www.safc.com/",
    "crestURL": "http://upload.wikimedia.org/wikipedia/de/6/60/AFC_Sunderland.svg",
    "stadium": "Stadium of Light",
    "latlng": [
      54.9144,
      -1.3882
    ],
    "pubs": [
      {
        "name": "The Victory PubThe New Democratic Club",
        "address": "",
        "phoneNumber": "",
        "website": "",
        "latlng": [
          
          
        ]
      },
      {
        "name": "The New Democratic Club",
        "address": "",
        "phoneNumber": "",
        "website": "",
        "latlng": [
         
         
       ]
      },
      {
        "name": "The Cambridge",
        "address": "",
        "phoneNumber": "",
        "website": "",
        "latlng": [
          
          
        ]
      }
    ],
    "foodOutlets": [
      {
        "name": "Monsoon Kitchen",
        "address": "",
        "phoneNumber": "",
        "website": "",
        "latlng": [
          
          
        ]
      },
      {
        "name": "Italian Kitchen",
        "address": "",
        "phoneNumber": "",
        "website": "",
        "latlng": [
         
        
       ]
      }
    ],
    "hotels": [
      {
        "name": "Hilton Garden Inn Sunderland",
        "address": "",
        "phoneNumber": "",
        "website": "",
        "latlng": [
          
          
        ]
      },
      {
        "name": "Sunderland Marriott Hotel",
        "address": "",
        "phoneNumber": "",
        "website": "",
        "latlng": [
         
         
       ]
      }
    ]
  },

  { 
    "name": "Swansea City FC",
    "code": "SWA",
    "website": "http://www.swanseacity.net/",
    "crestURL": "http://upload.wikimedia.org/wikipedia/de/a/ab/Swansea_City_Logo.svg",
    "stadium": "Liberty Stadium",
    "latlng": [
      51.6422,
      -3.9351
    ],
    "pubs": [
      {
        "name": "Bank Statement",
        "address": "",
        "phoneNumber": "",
        "website": "",
        "latlng": [
          
          
        ]
      },
      {
        "name": "Yates’s",
        "address": "",
        "phoneNumber": "",
        "website": "",
        "latlng": [
         
         
       ]
      },
      {
        "name": "The No Sign Bar",
        "address": "",
        "phoneNumber": "",
        "website": "",
        "latlng": [
          
          
        ]
      }
    ],
    "foodOutlets": [
      {
        "name": "Frankie & Bennys",
        "address": "",
        "phoneNumber": "",
        "website": "",
        "latlng": [
          
          
        ]
      },
      {
        "name": "Harvester",
        "address": "",
        "phoneNumber": "",
        "website": "",
        "latlng": [
         
        
       ]
      }
    ],
    "hotels": [
      {
        "name": "Mercure Swansea Hotel",
        "address": "",
        "phoneNumber": "",
        "website": "",
        "latlng": [
          
          
        ]
      },
      {
        "name": "The Grand Hotel",
        "address": "",
        "phoneNumber": "",
        "website": "",
        "latlng": [
         
         
       ]
      }
    ]
  },

  { 
    "name": "Tottenham Hotspur FC",
    "code": "THFC",
    "website": "http://www.tottenhamhotspur.com/",
    "crestURL": "http://upload.wikimedia.org/wikipedia/de/b/b4/Tottenham_Hotspur.svg",
    "stadium": "White Hart Lane",
    "latlng": [
      51.603333,
      -0.065833
    ],
    "pubs": [
      {
        "name": "Harringey Irish Club",
        "address": "",
        "phoneNumber": "",
        "website": "",
        "latlng": [
          
          
        ]
      },
      {
        "name": "Three Compasses ",
        "address": "",
        "phoneNumber": "",
        "website": "",
        "latlng": [
         
         
       ]
      },
      {
        "name": "The Elmhust",
        "address": "",
        "phoneNumber": "",
        "website": "",
        "latlng": [
          
          
        ]
      }
    ],
    "foodOutlets": [
      {
        "name": "Sakunthala's Pan Asia",
        "address": "",
        "phoneNumber": "",
        "website": "",
        "latlng": [
          
          
        ]
      },
      {
        "name": "White Hart Lane Jerk Centre",
        "address": "",
        "phoneNumber": "",
        "website": "",
        "latlng": [
         
        
       ]
      }
    ],
    "hotels": [
      {
        "name": "Premier Inn London Edmonton",
        "address": "",
        "phoneNumber": "",
        "website": "",
        "latlng": [
          
          
        ]
      },
      {
        "name": "Premier Inn London Tottenham Hale Hotel",
        "address": "",
        "phoneNumber": "",
        "website": "",
        "latlng": [
         
         
       ]
      }
    ]
  },

  { 
    "name": "Watford FC",
    "code": "WAT",
    "website": "https://www.watfordfc.com/",
    "crestURL": "https://upload.wikimedia.org/wikipedia/en/e/e2/Watford.svg",
    "stadium": "Vicarage Road",
    "latlng": [
      51.649836,
      -0.401486
    ],
    "pubs": [
      {
        "name": "The Oddfellows",
        "address": "",
        "phoneNumber": "",
        "website": "",
        "latlng": [
          
          
        ]
      },
      {
        "name": "Moon Under Water",
        "address": "",
        "phoneNumber": "",
        "website": "",
        "latlng": [
         
         
       ]
      },
      {
        "name": "Yates's",
        "address": "",
        "phoneNumber": "",
        "website": "",
        "latlng": [
          
          
        ]
      }
    ],
    "foodOutlets": [
      {
        "name": "Kasturi",
        "address": "",
        "phoneNumber": "",
        "website": "",
        "latlng": [
          
          
        ]
      },
      {
        "name": "Patwarls",
        "address": "",
        "phoneNumber": "",
        "website": "",
        "latlng": [
         
        
       ]
      }
    ],
    "hotels": [
      {
        "name": "Premier Inn Watford Croxley Green",
        "address": "",
        "phoneNumber": "",
        "website": "",
        "latlng": [
          
          
        ]
      },
      {
        "name": "Holiday Inn London - Watford Junction",
        "address": "",
        "phoneNumber": "",
        "website": "",
        "latlng": [
         
         
       ]
      }
    ]
  },

  { 
    "name": "West Bromwich Albion FC",
    "code": "WBA",
    "website": "http://www.wba.co.uk/",
    "crestURL": "http://upload.wikimedia.org/wikipedia/de/8/8b/West_Bromwich_Albion.svg",
    "stadium": "The Hawthorns",
    "latlng": [
      52.509167,
      -1.963889
    ],
    "pubs": [
      {
        "name": "The Royal Oak",
        "address": "",
        "phoneNumber": "",
        "website": "",
        "latlng": [
          
          
        ]
      },
      {
        "name": "Park Inn",
        "address": "",
        "phoneNumber": "",
        "website": "",
        "latlng": [
         
         
       ]
      },
      {
        "name": "The Vine",
        "address": "",
        "phoneNumber": "",
        "website": "",
        "latlng": [
          
          
        ]
      }
    ],
    "foodOutlets": [
      {
        "name": "McDonald's",
        "address": "",
        "phoneNumber": "",
        "website": "",
        "latlng": [
          
          
        ]
      },
      {
        "name": "Kebub",
        "address": "",
        "phoneNumber": "",
        "website": "",
        "latlng": [
         
        
       ]
      }
    ],
    "hotels": [
      {
        "name": "Park Inn",
        "address": "",
        "phoneNumber": "",
        "website": "",
        "latlng": [
          
          
        ]
      },
      {
        "name": "Premier Inn West Bromwich Central",
        "address": "",
        "phoneNumber": "",
        "website": "",
        "latlng": [
         
         
       ]
      }
    ]
  },

  { 
    "name": "West Ham United FC",
    "code": "WHU",
    "website": "https://www.whufc.com/",
    "crestURL": "http://upload.wikimedia.org/wikipedia/de/e/e0/West_Ham_United_FC.svg",
    "stadium": "London Stadium",
    "latlng": [
      51.538611,
      -0.016389
    ],
    "pubs": [
      {
        "name": "Golden Grove",
        "address": "",
        "phoneNumber": "",
        "website": "",
        "latlng": [
          
          
        ]
      },
      {
        "name": "J J Moon's",
        "address": "",
        "phoneNumber": "",
        "website": "",
        "latlng": [
         
         
       ]
      },
      {
        "name": "The Langthorne",
        "address": "",
        "phoneNumber": "",
        "website": "",
        "latlng": [
          
          
        ]
      }
    ],
    "foodOutlets": [
      {
        "name": "Forman's",
        "address": "",
        "phoneNumber": "",
        "website": "",
        "latlng": [
          
          
        ]
      },
      {
        "name": "The Podium Bar & Kitchen",
        "address": "",
        "phoneNumber": "",
        "website": "",
        "latlng": [
         
        
       ]
      }
    ],
    "hotels": [
      {
        "name": "Premier Inn London Wembley Stadium",
        "address": "",
        "phoneNumber": "",
        "website": "",
        "latlng": [
          
          
        ]
      },
      {
        "name": "Holiday Inn London - Wembley",
        "address": "",
        "phoneNumber": "",
        "website": "",
        "latlng": [
         
         
       ]
      }
    ]
  }
]